{
    "version":  1,
    "generated_at_utc":  "2026-03-31T05:51:38.0788439Z",
    "rules":  {
                  "file_length":  {
                                      "soft_limit":  600,
                                      "hard_limit":  900,
                                      "files":  {
                                                    "scripts/app/battlefield/battlefield_coordinator.gd":  727,
                                                    "scripts/app/battlefield/battlefield_hud_effect_formatter_support.gd":  614,
                                                    "scripts/app/battlefield/battlefield_hud_shop_inventory_view.gd":  664,
                                                    "scripts/combat/combat_manager.gd":  656,
                                                    "scripts/combat/combat_movement_service.gd":  651,
                                                    "scripts/domain/combat/combat_targeting.gd":  648,
                                                    "scripts/unit_augment/unit_augment_buff_manager.gd":  661,
                                                    "scripts/unit_augment/unit_augment_unit_state_service.gd":  1187
                                                },
                                      "summary":  {
                                                      "total_files":  8,
                                                      "over_900_files":  1,
                                                      "between_601_and_900_files":  7
                                                  }
                                  },
                  "scene_first_ui":  {
                                         "scope":  [
                                                       "scripts/main",
                                                       "scripts/ui",
                                                       "scripts/board"
                                                   ],
                                         "patterns":  [
                                                          "Control.new",
                                                          "Label.new",
                                                          "Button.new",
                                                          "LinkButton.new",
                                                          "LineEdit.new",
                                                          "ProgressBar.new",
                                                          "RichTextLabel.new",
                                                          "ColorRect.new",
                                                          "PanelContainer.new",
                                                          "VBoxContainer.new",
                                                          "HBoxContainer.new",
                                                          "GridContainer.new",
                                                          "MarginContainer.new",
                                                          "ScrollContainer.new",
                                                          "TextureRect.new"
                                                      ],
                                         "files":  {

                                                   },
                                         "total_occurrences":  0,
                                         "total_files":  0
                                     },
                  "root_lookup":  {
                                      "pattern":  "_get_root_node(",
                                      "files":  {

                                                },
                                      "total_occurrences":  0,
                                      "total_files":  0
                                  },
                  "dynamic_call":  {
                                       "pattern":  "call(",
                                       "files":  {
                                                     "scripts/battle/battlefield_renderer.gd":  1,
                                                     "scripts/battle/drag_controller.gd":  5,
                                                     "scripts/combat/combat_manager.gd":  13,
                                                     "scripts/combat/combat_targeting.gd":  1,
                                                     "scripts/core/object_pool.gd":  1,
                                                     "scripts/ui/battle_bench_ui.gd":  1,
                                                     "scripts/unit/unit_base.gd":  16,
                                                     "scripts/unit/unit_combat.gd":  3,
                                                     "scripts/unit/unit_movement.gd":  1,
                                                     "scripts/vfx/vfx_factory.gd":  7
                                                 },
                                       "total_occurrences":  49,
                                       "total_files":  10
                                   }
              }
}